identity_sync/__init__.py
identity_sync/APIs/__init__.py
identity_sync/APIs/api_format.py
identity_sync/APIs/utils/__init__.py
identity_sync/APIs/utils/generate_code.py
identity_sync/Nash/__init__.py
identity_sync/Nash/nash.py
identity_sync/Resources/KYC.py
identity_sync/Resources/__init__.py
identity_sync/Resources/identity.py
identity_sync/Resources/operations.py
identity_sync/Resources/resource.py
nashidentitysync-0.0.2.dist-info/LICENSE
nashidentitysync-0.0.2.dist-info/METADATA
nashidentitysync-0.0.2.dist-info/WHEEL
nashidentitysync-0.0.2.dist-info/top_level.txt
nashidentitysync-0.0.2.dist-info/RECORD
